mirage_bench/__init__.py
mirage_bench/logging.py
mirage_bench/util.py
mirage_bench/evaluate/__init__.py
mirage_bench/evaluate/automatic_answer_overlap.py
mirage_bench/evaluate/automatic_fluency.py
mirage_bench/evaluate/context_grounding.py
mirage_bench/evaluate/context_map_recall.py
mirage_bench/evaluate/language_detection.py
mirage_bench/evaluate/pairwise_llm_judge.py
mirage_bench/evaluate/reranker_score.py
mirage_bench/evaluate/rouge_and_blue.py
mirage_bench/evaluate/tokenizer.py
mirage_bench/evaluate/util.py
mirage_bench/generate/__init__.py
mirage_bench/generate/anyscale.py
mirage_bench/generate/azure_openai.py
mirage_bench/generate/base.py
mirage_bench/generate/claude.py
mirage_bench/generate/cohere.py
mirage_bench/generate/gemini.py
mirage_bench/generate/openai.py
mirage_bench/generate/vllm.py
mirage_bench/leaderboard/__init__.py
mirage_bench/leaderboard/bradley_terry.py
mirage_bench/leaderboard/llm_judge.py
mirage_bench/leaderboard/regression.py
mirage_bench/leaderboard/util.py
mirage_bench-0.0.4.dist-info/licenses/LICENSE
mirage_bench-0.0.4.dist-info/METADATA
mirage_bench-0.0.4.dist-info/WHEEL
mirage_bench-0.0.4.dist-info/top_level.txt
mirage_bench-0.0.4.dist-info/RECORD
