Metadata-Version: 2.4
Name: mirage-bench
Version: 0.0.4
Summary: A RAG-based benchmark for multilingual question answering.
Author-email: Nandan Thakur <nandant@gmail.com>, Suleman Kazi <suleman@vectara.com>, Amin Ahmad <amin@vectara.com>
License:                                  Apache License
Project-URL: Homepage, https://github.com/vectara/mirage-bench
Keywords: RAG,multilingual,question answering,benchmark,deep learning
Classifier: Intended Audience :: Science/Research
Classifier: License :: OSI Approved :: Apache Software License
Classifier: Programming Language :: Python :: 3.10
Classifier: Programming Language :: Python :: 3.11
Classifier: Programming Language :: Python :: 3.12
Classifier: Topic :: Scientific/Engineering :: Artificial Intelligence
Requires-Python: >=3.10
License-File: LICENSE
Requires-Dist: openai
Requires-Dist: vllm
Requires-Dist: transformers
Requires-Dist: datasets
Requires-Dist: stanza
Requires-Dist: sentencex
Requires-Dist: lingua-language-detector
Requires-Dist: FlagEmbedding
Requires-Dist: anthropic
Requires-Dist: google-generativeai
Requires-Dist: cohere
Requires-Dist: choix
Requires-Dist: scikit-learn
Requires-Dist: multilingual-rouge
Requires-Dist: evaluate
Requires-Dist: pytrec-eval-terrier
Dynamic: license-file
